dynamo3/__init__.py
dynamo3/batch.py
dynamo3/connection.py
dynamo3/constants.py
dynamo3/exception.py
dynamo3/fields.py
dynamo3/rate.py
dynamo3/result.py
dynamo3/testing.py
dynamo3/types.py
dynamo3/util.py
dynamo3-1.0.0.dist-info/LICENSE
dynamo3-1.0.0.dist-info/METADATA
dynamo3-1.0.0.dist-info/WHEEL
dynamo3-1.0.0.dist-info/entry_points.txt
dynamo3-1.0.0.dist-info/top_level.txt
dynamo3-1.0.0.dist-info/RECORD
