Metadata-Version: 2.1
Name: dynamo3
Version: 1.0.0
Summary: Python 3 compatible library for DynamoDB
Home-page: http://github.com/stevearc/dynamo3
Author: Steven Arcangeli
Author-email: stevearc@stevearc.com
License: MIT
Keywords: aws dynamo dynamodb
Platform: UNKNOWN
Classifier: Development Status :: 4 - Beta
Classifier: Intended Audience :: Developers
Classifier: License :: OSI Approved :: MIT License
Classifier: Operating System :: OS Independent
Classifier: Programming Language :: Python
Classifier: Programming Language :: Python :: 3
Classifier: Programming Language :: Python :: 3.6
Classifier: Programming Language :: Python :: 3.7
Classifier: Programming Language :: Python :: 3.8
Requires-Python: >=3.6
Requires-Dist: botocore (>=0.89.0)
